buildutilities
