Metadata-Version: 1.0
Name: build-utilities
Version: 0.3.2
Summary: Build utilities for python and go projects.
Home-page: http://github.com/aacebedo/build-utilities
Author: Alexandre ACEBEDO
Author-email: Alexandre ACEBEDO
License: LGPLv3
Keywords: build go python
Platform: UNKNOWN
